scanmate/__init__.py
scanmate/cli.py
scanmate-0.1.0.dist-info/METADATA
scanmate-0.1.0.dist-info/WHEEL
scanmate-0.1.0.dist-info/entry_points.txt
scanmate-0.1.0.dist-info/RECORD
