Metadata-Version: 2.3
Name: scanmate
Version: 0.1.0
Summary: 
Author: markus
Author-email: datamastery87@gmail.com
Requires-Python: >=3.11
Classifier: Programming Language :: Python :: 3
Classifier: Programming Language :: Python :: 3.11
Classifier: Programming Language :: Python :: 3.12
Classifier: Programming Language :: Python :: 3.13
Requires-Dist: pyperclip (>=1.9.0,<2.0.0)
Requires-Dist: toml (>=0.10.2,<0.11.0)
Requires-Dist: typer (>=0.15.1,<0.16.0)
